mapfishpluginclient
