Metadata-Version: 1.0
Name: mapfish.plugin.client
Version: 0.2
Summary: Client plugin of the MapFish Framework.
Home-page: http://www.mapfish.org
Author: Camptocamp
Author-email: info@camptocamp.com
License: GPLv3
Keywords: MapFish JavaScript GeoExt OpenLayers ExtJS
Platform: UNKNOWN
Classifier: Development Status :: 3 - Alpha
Classifier: Intended Audience :: Developers
Classifier: Intended Audience :: Science/Research
Classifier: License :: OSI Approved :: GNU General Public License (GPL)
Classifier: Operating System :: OS Independent
Classifier: Programming Language :: Python
Classifier: Programming Language :: JavaScript
Classifier: Framework :: Paste
Classifier: Topic :: Scientific/Engineering :: GIS
Classifier: Topic :: Internet :: WWW/HTTP
Classifier: Topic :: Internet :: WWW/HTTP :: Dynamic Content
Classifier: Topic :: Internet :: WWW/HTTP :: WSGI
Classifier: Topic :: Software Development :: Libraries :: Python Modules
